toltec/__init__.py
toltec/__main__.py
toltec/bash.py
toltec/builder.py
toltec/ipk.py
toltec/py.typed
toltec/recipe.py
toltec/repo.py
toltec/util.py
toltec/version.py
toltec/hooks/__init__.py
toltec/hooks/install_lib.py
toltec/hooks/patch_rm2fb.py
toltec/hooks/py.typed
toltec/hooks/reload_oxide_apps.py
toltec/hooks/strip.py
toltec/recipe_parsers/__init__.py
toltec/recipe_parsers/bash.py
toltec/recipe_parsers/py.typed
toltecmk-0.3.7.dist-info/licenses/LICENSE
toltecmk-0.3.7.dist-info/METADATA
toltecmk-0.3.7.dist-info/WHEEL
toltecmk-0.3.7.dist-info/entry_points.txt
toltecmk-0.3.7.dist-info/top_level.txt
toltecmk-0.3.7.dist-info/RECORD
