Metadata-Version: 2.4
Name: toltecmk
Version: 0.3.7
Summary: Build system used for the Toltec community repository
Author-email: Mattéo Delabre <git.matteo@delab.re>, Eeems <eeems@eeems.email>
Project-URL: Homepage, https://github.com/toltec-dev/build
Project-URL: Bug Tracker, https://github.com/toltec-dev/build/issues
Keywords: build-tooling,packaging,distribution
Classifier: Development Status :: 4 - Beta
Classifier: Intended Audience :: Developers
Classifier: License :: OSI Approved :: MIT License
Classifier: Operating System :: POSIX :: Linux
Classifier: Programming Language :: Python :: 3
Classifier: Programming Language :: Python :: 3.11
Classifier: Programming Language :: Python :: 3.12
Classifier: Programming Language :: Python :: 3.13
Classifier: Programming Language :: Python :: 3 :: Only
Classifier: Topic :: Software Development :: Build Tools
Classifier: Topic :: System :: Archiving :: Packaging
Requires-Python: >=3.11
License-File: LICENSE
Requires-Dist: docker==7.1.0
Requires-Dist: python-dateutil==2.9.0.post0
Requires-Dist: pyelftools==0.32
Dynamic: license-file
